nucleoseeker/__init__.py
nucleoseeker/check_tool.py
nucleoseeker/columns.py
nucleoseeker/dataset_creator.py
nucleoseeker/dataset_download.py
nucleoseeker/individual_structure_filter.py
nucleoseeker/metadata_filter.py
nucleoseeker/structure_comparison_filter.py
nucleoseeker/utils.py
nucleoseeker-0.1.3.dist-info/LICENSE
nucleoseeker-0.1.3.dist-info/METADATA
nucleoseeker-0.1.3.dist-info/WHEEL
nucleoseeker-0.1.3.dist-info/entry_points.txt
nucleoseeker-0.1.3.dist-info/top_level.txt
nucleoseeker-0.1.3.dist-info/RECORD
