Metadata-Version: 2.1
Name: nucleoseeker
Version: 0.1.3
Summary: Precision filtering of RNA databases to curate high-quality datasets
Home-page: https://github.com/theuutkarsh/nucleoseeker
Author: Utkarsh Upadhyay
Author-email: u.upadhyay@fz-juelich.de
Classifier: License :: OSI Approved :: MIT License
Classifier: Operating System :: POSIX
Classifier: Operating System :: POSIX :: Linux
Classifier: Operating System :: MacOS :: MacOS X
Classifier: Operating System :: Unix
Classifier: Programming Language :: Python :: 3.12
Requires-Python: >=3.6
License-File: LICENSE
Requires-Dist: numpy (>=1.25.1)
Requires-Dist: pandas (>=2.0.3)
Requires-Dist: Requests (>=2.32.1)
Requires-Dist: biopython (>=1.83)
